odoo/addons/ddmrp_purchase_hide_onhand_status/README.rst
odoo/addons/ddmrp_purchase_hide_onhand_status/__init__.py
odoo/addons/ddmrp_purchase_hide_onhand_status/__manifest__.py
odoo/addons/ddmrp_purchase_hide_onhand_status/i18n/ddmrp_purchase_hide_onhand_status.pot
odoo/addons/ddmrp_purchase_hide_onhand_status/i18n/es.po
odoo/addons/ddmrp_purchase_hide_onhand_status/i18n/it.po
odoo/addons/ddmrp_purchase_hide_onhand_status/models/__init__.py
odoo/addons/ddmrp_purchase_hide_onhand_status/models/purchase_order.py
odoo/addons/ddmrp_purchase_hide_onhand_status/readme/CONTRIBUTORS.md
odoo/addons/ddmrp_purchase_hide_onhand_status/readme/DESCRIPTION.md
odoo/addons/ddmrp_purchase_hide_onhand_status/static/description/icon.png
odoo/addons/ddmrp_purchase_hide_onhand_status/static/description/index.html
odoo/addons/ddmrp_purchase_hide_onhand_status/tests/__init__.py
odoo/addons/ddmrp_purchase_hide_onhand_status/tests/test_ddmrp_purchase_hide_onhand_status.py
odoo/addons/ddmrp_purchase_hide_onhand_status/views/purchase_order_view.xml
odoo_addon_ddmrp_purchase_hide_onhand_status-18.0.1.0.0.2.dist-info/METADATA
odoo_addon_ddmrp_purchase_hide_onhand_status-18.0.1.0.0.2.dist-info/WHEEL
odoo_addon_ddmrp_purchase_hide_onhand_status-18.0.1.0.0.2.dist-info/top_level.txt
odoo_addon_ddmrp_purchase_hide_onhand_status-18.0.1.0.0.2.dist-info/RECORD
